{
    "endpoints": [
        {
            "name": "Auth",
            "methods": [
                {
                    "MethodName": "login",
                    "HTTPMethod": "POST",
                    "URI": "/auth/login",
                    "RequiresOAuth": "N",
                    "parameters": [
                        {
                            "Name": "fb_user_id",
                            "Required": "Y",
                            "Default": "",
                            "Type": "string",
                            "Description": "FaceBook user id"
                        },
                        {
                            "Name": "fb_access_token",
                            "Required": "Y",
                            "Default": "",
                            "Type": "string",
                            "Description": "FaceBook access token"
                        }                        
                    ]
                },
                {
                    "MethodName": "logout",
                    "HTTPMethod": "POST",
                    "URI": "/auth/logout/",
                    "RequiresOAuth": "Y",
                    "parameters": [
                        {
                            "Name": "access_token",
                            "Required": "Y",
                            "Default": "",
                            "Type": "string",
                            "Description": "Day ID"
                        }
                    ]
                }
            ]
        },
        {
            "name": "User methods",
            "methods": [
                {
                    "MethodName": "Get all days",
                    "HTTPMethod": "GET",
                    "URI": "/day/",
                    "RequiresOAuth": "Y",
                    "parameters": []
                },
                {
                    "MethodName": "Get day by ID",
                    "HTTPMethod": "GET",
                    "URI": "/day/item/",
                    "RequiresOAuth": "Y",
                    "parameters": [
                        {
                            "Name": "id",
                            "Required": "Y",
                            "Default": "",
                            "Type": "integer",
                            "Description": "Day ID"
                        }
                    ]
                },                
                {
                    "MethodName": "Create new day",
                    "Synopsis": "Bla-bla-bla",
                    "HTTPMethod": "POST",
                    "URI": "day/create",
                    "RequiresOAuth": "Y",
                    "parameters": [
                        {
                            "Name": "title",
                            "Required": "Y",
                            "Default": "",
                            "Type": "string",
                            "Description": "Day title (255 symbols)"
                        },
                        {
                            "Name": "description",
                            "Required": "Y",
                            "Default": "",
                            "Type": "string",
                            "Description": "Day description (1023 symbols)"
                        }
                    ]
                },
                {
                    "MethodName": "Update day",
                    "Synopsis": "Bla-bla-bla",
                    "HTTPMethod": "POST",
                    "URI": "day/update",
                    "RequiresOAuth": "Y",
                    "parameters": [
                        {
                            "Name": "id",
                            "Required": "Y",
                            "Default": "",
                            "Type": "integer",
                            "Description": "Day ID"
                        },
                        {
                            "Name": "title",
                            "Required": "Y",
                            "Default": "",
                            "Type": "string",
                            "Description": "Day title (255 symbols)"
                        },
                        {
                            "Name": "description",
                            "Required": "Y",
                            "Default": "",
                            "Type": "string",
                            "Description": "Day description (1023 symbols)"
                        }
                    ]
                },
                {
                    "MethodName": "Delete day by ID",
                    "HTTPMethod": "POST",
                    "URI": "/day/delete/",
                    "RequiresOAuth": "Y",
                    "parameters": [
                        {
                            "Name": "id",
                            "Required": "Y",
                            "Default": "",
                            "Type": "integer",
                            "Description": "Day ID"
                        }
                    ]
                },
                {
                    "MethodName": "Restore day by ID",
                    "HTTPMethod": "POST",
                    "URI": "/day/restore/",
                    "RequiresOAuth": "Y",
                    "parameters": [
                        {
                            "Name": "id",
                            "Required": "Y",
                            "Default": "",
                            "Type": "integer",
                            "Description": "Day ID"
                        }
                    ]
                }
            ]
        }        
    ]
}